CentriVision/Centrifinder.py
CentriVision/Community_detection.py
CentriVision/Count_file.py
CentriVision/Dotplot - 副本.py
CentriVision/Dotplot-.py
CentriVision/Dotplot-poly.py
CentriVision/Dotplot.py
CentriVision/Dotplot1.py
CentriVision/EdistAln.py
CentriVision/EdistDot.py
CentriVision/Get_centgff.py
CentriVision/Get_centr.py
CentriVision/Get_centri - 副本 (2).py
CentriVision/Get_centri.py
CentriVision/Get_repeat.py
CentriVision/HOR.py
CentriVision/Heatmap - 副本.py
CentriVision/Heatmap.py
CentriVision/Ic_Significance.py
CentriVision/Monomer.py
CentriVision/Palindromic.py
CentriVision/Repeat_community_map.py
CentriVision/SatAge.py
CentriVision/SeqSigil.py
CentriVision/TRF.py
CentriVision/TRF2gff.py
CentriVision/__init__.py
CentriVision/bez.py
CentriVision/conf.ini
CentriVision/getNCBI.py
CentriVision/getPASA.py
CentriVision/run.py
CentriVision/Lib/__init__.py
CentriVision/Lib/myalign.so
CentriVision/Lib/palindrome.so
CentriVision/example/Centrifinder.conf
CentriVision/example/Community_detection.conf
CentriVision/example/Count_file.conf
CentriVision/example/Dotplot.conf
CentriVision/example/EdistAln.conf
CentriVision/example/EdistDot.conf
CentriVision/example/Get_centgff.conf
CentriVision/example/Get_centri.conf
CentriVision/example/Get_repeat.conf
CentriVision/example/HOR.conf
CentriVision/example/Heatmap.conf
CentriVision/example/Ic_Significance.conf
CentriVision/example/Monomer.conf
CentriVision/example/Palindromic.conf
CentriVision/example/Repeat_community_map.conf
CentriVision/example/SatAge.conf
CentriVision/example/SeqSigil.conf
CentriVision/example/TRF.conf
CentriVision/example/__init__.py
CentriVision/example/arial.ttf
CentriVision/example/getNCBI.conf
CentriVision/example/getPASA.conf
CentriVision/example/score.xlsx
CentriVision/example_data/NIP-T2T-osa2.fa
CentriVision/example_data/__init__.py
CentriVision/example_data/osa.TRF.gff
CentriVision/example_data/osa.lens
centrivision-1.0.1.dist-info/licenses/LICENSE
centrivision-1.0.1.dist-info/METADATA
centrivision-1.0.1.dist-info/WHEEL
centrivision-1.0.1.dist-info/entry_points.txt
centrivision-1.0.1.dist-info/top_level.txt
centrivision-1.0.1.dist-info/zip-safe
centrivision-1.0.1.dist-info/RECORD
