Metadata-Version: 2.4
Name: CentriVision
Version: 1.0.1
Summary: CentriVision
Author: charles_kiko
Author-email: charles_kiko@163.com
License: BSD License
Classifier: Intended Audience :: Science/Research
Classifier: Programming Language :: Python :: 3
Classifier: License :: OSI Approved :: BSD License
Classifier: Operating System :: OS Independent
License-File: LICENSE
Requires-Dist: pandas
Requires-Dist: numpy
Requires-Dist: biopython
Requires-Dist: matplotlib
Requires-Dist: scipy
Requires-Dist: interval
Requires-Dist: seaborn
Requires-Dist: tqdm
Requires-Dist: pysam
Requires-Dist: logomaker
Requires-Dist: python-Levenshtein
Dynamic: author
Dynamic: author-email
Dynamic: classifier
Dynamic: description
Dynamic: description-content-type
Dynamic: license
Dynamic: license-file
Dynamic: requires-dist
Dynamic: summary
